README.md
hello_world_api1.py
setup.py
gu_tea.egg-info/PKG-INFO
gu_tea.egg-info/SOURCES.txt
gu_tea.egg-info/dependency_links.txt
gu_tea.egg-info/requires.txt
gu_tea.egg-info/top_level.txt